fish_collector.py
fish_exposer.py
test_integration.py
test_unit.py
BBS_firstassignment-0.0.3.dist-info/METADATA
BBS_firstassignment-0.0.3.dist-info/WHEEL
BBS_firstassignment-0.0.3.dist-info/top_level.txt
BBS_firstassignment-0.0.3.dist-info/RECORD
