Metadata-Version: 2.1
Name: BBS-firstassignment
Version: 0.0.3
Requires-Dist: requests
Requires-Dist: importlib-metadata ; python_version == "3.8"
